{
  "id" : "qnxztp4ikukufnyiyvgqnxhopiestvjqemyucfukrcr",
  "meta" : {
    "title" : "daczefs7deg",
    "description" : "",
    "posterID" : "y2efqt0v8m5kf9vuuchb4r6u1g7phabicnobi1oa",
    "companyID" : "z4j5ympw3loafiij0vw8s2shfijnkxpp9vmuieen",
    "editorsId" : [ "ehmk8418dwkjahjdnotpyk", "", "kqxokm2e1itp93xkkcjdzt" ],
    "confirmationMesssage" : "tpb7hxdysd9jehtc3l9rpqiwabxlg1ixj7ztwrzsnkkrvxohy",
    "questionsNumber" : 15
  },
  "questions" : [ {
    "type" : "TEXT",
    "helpText" : "4fjzgs00seufxirbzduyspzjjmww6cl3p3g5awfxw",
    "placeholder" : "rpzq1yzwm0qelqhutpowmxruvng",
    "title" : "dl3pxpx7yi4rtpitquacfevzys516pyotndlw4a",
    "id" : 6491923,
    "isRequired" : false
  }, {
    "type" : "TEXT",
    "helpText" : "rdgzahultnqn4cipgl",
    "placeholder" : "oby5wqw70qsakbr",
    "title" : "iril19nft6klvnppymic5spu0kln9rtxnyd4jgghw0gnm8mrdfsqwedg9wi2cpalknvvfcdbp13r9trba8legwufof",
    "id" : 7323809,
    "isRequired" : false
  }, {
    "type" : "TEXTAREA",
    "helpText" : "ne5tejnzneug5ef8",
    "placeholder" : "4yofnid1k",
    "title" : "0utpqgct1ja4oiusoc1snyzns9unk5",
    "id" : 7713618,
    "isRequired" : true
  }, {
    "type" : "TEXTAREA",
    "helpText" : "6up3enxmxxex37fi",
    "placeholder" : "mr37gslxvdehhc18becuthn72evdiz",
    "title" : "okp4pun7rjm465tbn7bi0btgzcec6ebggxwqppsepyizwqrzqb0ndd7pxkh34g0ewa6jcpmocqkz7zv17klzmigt5ky",
    "id" : 5372215,
    "isRequired" : true
  }, {
    "type" : "TEXTAREA",
    "helpText" : "yfrvxhd",
    "placeholder" : "emd0lmmid82vdtilxam",
    "title" : "7jfardum41is0hkgm3cbfgkkyz",
    "id" : 3193733,
    "isRequired" : false
  }, {
    "type" : "TEXTAREA",
    "helpText" : "j3umqduu0zw",
    "placeholder" : "5dvi48foxhlal5wt",
    "title" : "bghewnhumpaoxhlwgdzuppv6ncysxsfa1kluxwzwdb39cpsg1ftlkqvdlaqdlkcl4hjawd",
    "id" : 533566,
    "isRequired" : true
  }, {
    "type" : "TEXTAREA",
    "helpText" : "8wfzce09flxhr1uzsy9gj2fst",
    "placeholder" : "ktzsvmxk6ett07xh",
    "title" : "6fzgzu4081tekdvuyc9rvctve9ttizzn040f606us24j2urb8wksobcspdv8kd1p19r9tpyvoka2tmklgoj43bmnm4zebagzqnk",
    "id" : 6007138,
    "isRequired" : false
  }, {
    "type" : "TEXTAREA",
    "helpText" : "bzeclrfv7ovf89akdpwxq449dloex9",
    "placeholder" : "fdak0mv8wqivfuzj",
    "title" : "ltbuqn96mh28nx3kxlzwi5flibtkpbfrjqdow3jestqsaj3aypzyhf0pow2rwiamzbowc",
    "id" : 7272344,
    "isRequired" : false
  }, {
    "type" : "TEXTAREA",
    "helpText" : "ncyfptlx19ohohajvfssm7l",
    "placeholder" : "cvj8bg9",
    "title" : "laiigxcutu2wuyf98x4dnxdvjnl8et2x73bynysctorbsjzidxwqjuolpf",
    "id" : 155823,
    "isRequired" : true
  }, {
    "type" : "TEXTAREA",
    "helpText" : "gnpvuntn39rrzb",
    "placeholder" : "3cnl1cgl5n9",
    "title" : "pqcjzomtfnpgy1nmimboytm4gc3vsijflt02hywd13r1yk48bnqpwdczywtlx38ye7vg2zynglcmizwsx6hgm2a0tnjuec04wc4p",
    "id" : 521110,
    "isRequired" : true
  }, {
    "type" : "MULTIPLE_CHOICE",
    "helpText" : "sp0hhwf2aqreik7k8k",
    "placeholder" : "zhsn1w2efsnrvnqz99f8o67",
    "title" : "dhas8zbbaueik41skjlgpwk3je0b2spqhutjjdu5g8zwral",
    "id" : 1014293,
    "isRequired" : true,
    "options" : [ "Option 1", "Option 2", "Option 3", "Option 4", "Option 5", "Option 6", "Option 7", "Option 8", "Option 9", "Option 10", "Option 11" ]
  }, {
    "type" : "MULTIPLE_CHOICE",
    "helpText" : "arsgzzwhhmzi7uiypzxjexbdlubx2jycazjjho",
    "placeholder" : "eq4m83bypkhnnvdz7z8",
    "title" : "1xvo0tloqkl02s1ufgt4uglop5rcud46d3i",
    "id" : 3758474,
    "isRequired" : true,
    "options" : [ "Option 1", "Option 2", "Option 3", "Option 4" ]
  }, {
    "type" : "CHECKBOX",
    "helpText" : "1hyzqmkhenzdae7bsiorfjpkob4z0dwvbopuajvi",
    "placeholder" : "mhvaql0ibrtm6m8",
    "title" : "xytsdfkjyd40d3xrlkfpxr3xmqtc1gn0x3cuuc8xo718rymvdlihtoyttzjcjt",
    "id" : 9323244,
    "isRequired" : true,
    "options" : [ "Option 1 Check", "Option 2 Check", "Option 3 Check", "Option 4 Check", "Option 5 Check", "Option 6 Check" ]
  }, {
    "type" : "CHECKBOX",
    "helpText" : "bvpfc5u9e944brttf2csaoobl9brrbz2aj7fuc",
    "placeholder" : "nj6nnuk50t7ncbcsm7znfysamirmskthj",
    "title" : "yo51all9ixexp28um2vp0ldsttrkj66ua2rxkwhz6kujnzfnapzpkmse5jlzjr3x",
    "id" : 1258354,
    "isRequired" : false,
    "options" : [ "Option 1 Check", "Option 2 Check", "Option 3 Check", "Option 4 Check", "Option 5 Check", "Option 6 Check", "Option 7 Check", "Option 8 Check", "Option 9 Check", "Option 10 Check", "Option 11 Check", "Option 12 Check" ]
  }, {
    "type" : "DROPDOWN",
    "helpText" : "qqmxqiztqawmj88pp5h7yre",
    "placeholder" : "w1l790ch",
    "title" : "7qex72r1z9dk0ucxpfdvitcdb8sa0skj7ujyfdsnkxq30lpzaejxkd5vcgi1pz5flrir6gzb",
    "id" : 7904150,
    "isRequired" : true,
    "options" : [ "Option 1 Dropdown", "Option 2 Dropdown", "Option 3 Dropdown", "Option 4 Dropdown", "Option 5 Dropdown", "Option 6 Dropdown", "Option 7 Dropdown", "Option 8 Dropdown" ]
  } ]
}