{
  "id" : "lme6ccu5lzfgdiysqaggwfg4uposrjeokgfnscdy5uc",
  "meta" : {
    "title" : "xdntrhf3ow9dtrsqba4wrvk2lcpcit8obss6qyurf6ckbcs1qgvdiagrnjmctimbwu5uqp7p5s1ug",
    "description" : "eyq6kak1xk9mch0juhhsly1hzhtanjh0ldd7z",
    "companyID" : "rytkq4qhs0axbb6mfncqtackyeftqxqmqjshnmo9",
    "editorsId" : [ ],
    "confirmationMesssage" : "fqjg9jqxeefpm04wnkiotzc1zpv05",
    "questionsNumber" : 6
  },
  "questions" : [ {
    "type" : "MULTIPLE_CHOICE",
    "helpText" : "tgp1btonndnscbvs5aqlxypy",
    "placeholder" : "u53nc4ko",
    "title" : "bw3itekaqg2vacpibknuidmh4axwxe0tosaxxaplov",
    "id" : 6015021,
    "isRequired" : false,
    "hasOtherOption" : true,
    "options" : [ "Option 1", "Option 2", "Option 3", "Option 4", "Option 5", "Option 6", "Option 7", "Option 8", "Option 9", "Option 10", "Option 11", "Option 12" ]
  }, {
    "type" : "CHECKBOX",
    "helpText" : "b5cwyhwaytxmhun6pjrn9dst6nedslv1c",
    "placeholder" : "ttsuhwfhifmvs0enq9wiimwi9",
    "title" : "tqxffn3",
    "id" : 527430,
    "isRequired" : true,
    "hasOtherOption" : true,
    "options" : [ "Option 1 Check", "Option 2 Check", "Option 3 Check", "Option 4 Check", "Option 5 Check", "Option 6 Check", "Option 7 Check", "Option 8 Check", "Option 9 Check", "Option 10 Check", "Option 11 Check" ]
  }, {
    "type" : "DROPDOWN",
    "helpText" : "23ey",
    "placeholder" : "jlud5khqkdhqavsf5hxoecjjtp",
    "title" : "cskb8yhk5i6xdpwxwpr",
    "id" : 3370416,
    "isRequired" : true,
    "options" : [ "Option 1 Dropdown", "Option 2 Dropdown", "Option 3 Dropdown", "Option 4 Dropdown", "Option 5 Dropdown", "Option 6 Dropdown", "Option 7 Dropdown", "Option 8 Dropdown", "Option 9 Dropdown", "Option 10 Dropdown" ]
  }, {
    "type" : "DROPDOWN",
    "helpText" : "cq50ryh8rfxaxsh8kgcvuyljanhxm3",
    "placeholder" : "zwnlkjfko",
    "title" : "5kh0oa6oymddttmvkakyf3hpqmzjusnhoxe2loentl",
    "id" : 9035096,
    "isRequired" : false,
    "options" : [ "Option 1 Dropdown", "Option 2 Dropdown", "Option 3 Dropdown", "Option 4 Dropdown", "Option 5 Dropdown", "Option 6 Dropdown", "Option 7 Dropdown", "Option 8 Dropdown", "Option 9 Dropdown" ]
  }, {
    "type" : "DROPDOWN",
    "helpText" : "lzsctolgf6akjdbu1zisakcsqih4exohof1cfudwe",
    "placeholder" : "0ctd6p9",
    "title" : "lmvrmp0ln9rbx3zry2wr1ryzsylocdmivrrrpvfbcdfuqc2xsy6oc7tl1kgbycbplzkff9camqsush",
    "id" : 8676026,
    "isRequired" : false,
    "options" : [ "Option 1 Dropdown", "Option 2 Dropdown", "Option 3 Dropdown", "Option 4 Dropdown", "Option 5 Dropdown", "Option 6 Dropdown", "Option 7 Dropdown", "Option 8 Dropdown", "Option 9 Dropdown", "Option 10 Dropdown", "Option 11 Dropdown", "Option 12 Dropdown", "Option 13 Dropdown" ]
  }, {
    "type" : "DROPDOWN",
    "helpText" : "93bf1uzmbsjzrah",
    "placeholder" : "jjmq75sd8jt",
    "title" : "3wlhkr8jijzsluqxifkxwvjbllo3moar89hwke9mpiwewbmfyj8ngjmseyj4sogmjsh06rwvn1aem31jhbwftwhnkhyevj8pbjecd",
    "id" : 3138402,
    "isRequired" : true,
    "options" : [ "Option 1 Dropdown", "Option 2 Dropdown", "Option 3 Dropdown", "Option 4 Dropdown", "Option 5 Dropdown", "Option 6 Dropdown", "Option 7 Dropdown", "Option 8 Dropdown" ]
  } ]
}